dictionary/__init__.py
dictionary/dictionary.py
MertLaleci_directory-2.0.0.dist-info/METADATA
MertLaleci_directory-2.0.0.dist-info/WHEEL
MertLaleci_directory-2.0.0.dist-info/top_level.txt
MertLaleci_directory-2.0.0.dist-info/RECORD
