Metadata-Version: 2.1
Name: MertLaleci-directory
Version: 2.0.0
Summary: UNKNOWN
Author: Kadir Mert Laleci
License: UNKNOWN
Platform: UNKNOWN
Requires-Python: >=3.8
Requires-Dist: requests (>=2.23.0)
